CHANGES.txt
LICENSE.txt
MANIFEST.in
README.md
setup.py
admin_thumbnail/__init__.py
admin_thumbnail/thumb_admin.py
admin_thumbnail/locale/es/LC_MESSAGES/django.mo
admin_thumbnail/locale/es/LC_MESSAGES/django.po
admin_thumbnail/locale/pt_BR/LC_MESSAGES/django.mo
admin_thumbnail/locale/pt_BR/LC_MESSAGES/django.po
admin_thumbnail/static/thumb.css
admin_thumbnail/templates/thumb.html
django_admin_thumbnail.egg-info/PKG-INFO
django_admin_thumbnail.egg-info/SOURCES.txt
django_admin_thumbnail.egg-info/dependency_links.txt
django_admin_thumbnail.egg-info/not-zip-safe
django_admin_thumbnail.egg-info/requires.txt
django_admin_thumbnail.egg-info/top_level.txt