Metadata-Version: 1.1
Name: django-admin-thumbnail
Version: 1.0
Summary: Thumbnails for ImageFields in django admin.
Home-page: https://github.com/fjcaetano/django_admin_thumbnail
Author: Flávio Caetano
Author-email: flavio@vieiracaetano.com
License: MIT - see LICENSE.txt
Platform: any
Classifier: Environment :: Web Environment
Classifier: Framework :: Django
Classifier: Development Status :: 3 - Alpha
Classifier: License :: OSI Approved :: GNU General Public License (GPL)
Classifier: Natural Language :: Portuguese (Brazilian)
Classifier: Topic :: Internet :: WWW/HTTP :: Dynamic Content
